pdfextractor/__init__.py
pdfextractor/__main__.py
pdfextractor/cli.py
pdfextractor-0.1.dist-info/AUTHORS.rst
pdfextractor-0.1.dist-info/LICENSE
pdfextractor-0.1.dist-info/METADATA
pdfextractor-0.1.dist-info/WHEEL
pdfextractor-0.1.dist-info/dependency_links.txt
pdfextractor-0.1.dist-info/entry_points.txt
pdfextractor-0.1.dist-info/top_level.txt
pdfextractor-0.1.dist-info/RECORD
